README.rst
setup.cfg
setup.py
./__init__.py
./account.xml
./invoice.py
./invoice.xml
./tryton.cfg
./locale/de_DE.po
./tests/__init__.py
./tests/test_invoice.py
./view/configuration_form.xml
./view/invoice_form.xml
./view/pay_using_transaction_failed_form.xml
./view/pay_using_transaction_start_form.xml
fio_invoice_payment_gateway.egg-info/PKG-INFO
fio_invoice_payment_gateway.egg-info/SOURCES.txt
fio_invoice_payment_gateway.egg-info/dependency_links.txt
fio_invoice_payment_gateway.egg-info/entry_points.txt
fio_invoice_payment_gateway.egg-info/not-zip-safe
fio_invoice_payment_gateway.egg-info/requires.txt
fio_invoice_payment_gateway.egg-info/top_level.txt