Metadata-Version: 1.1
Name: fio-invoice-payment-gateway
Version: 4.0.4.0
Summary: Tryton module for invoice payment gateway integration
Home-page: https://www.fulfil.io
Author: Fulfil.IO INC.
Author-email: support@fulfil.io
License: BSD
Platform: UNKNOWN
Classifier: Development Status :: 4 - Beta
Classifier: Environment :: Plugins
Classifier: Intended Audience :: Developers
Classifier: License :: OSI Approved :: BSD License
Classifier: Natural Language :: English
Classifier: Operating System :: OS Independent
Classifier: Programming Language :: Python
Classifier: Framework :: Tryton
Classifier: Topic :: Office/Business
